<?xml version = '1.0' encoding = 'UTF-8'?>
<Diagram class="oracle.dbtools.crest.swingui.relational.DPVRelational" name="Relational_1" id="AB908175-AF9B-9E48-5DA2-9E4E8E2B10E1">
<createdBy>ugonzalez</createdBy>
<modifiedBy>ugonzalez</modifiedBy>
<createdTime>2018-02-14 16:53:20 UTC</createdTime>
<autoRoute>false</autoRoute>
<boxInbox>true</boxInbox>
<showLegend>false</showLegend>
<showLabels>false</showLabels>
<showRelAttributes>false</showRelAttributes>
<gridEnabled>false</gridEnabled>
<showGrid>false</showGrid>
<diagramColor>-1</diagramColor>
<display>false</display>
<notation>1</notation>
<showComments>true</showComments>
<objectViews>
<OView class="oracle.dbtools.crest.swingui.relational.TVTable" oid="0058314E-1B92-744B-E5D6-71B1FE4395EF" otype="Table" vid="0871EB03-7058-D831-988A-CEB9E9CF4390">
<hideElementsInCurrentOnly>false</hideElementsInCurrentOnly>
<bounds x="412" y="2275" width="341" height="729"/>
<useCustomFormat>true</useCustomFormat>
<useDefaultColor>false</useDefaultColor>
<backgroundColor>-26215</backgroundColor>
<foregroundColor>-16776961</foregroundColor>
<fonts itemClass="oracle.dbtools.crest.model.design.FontObjectWr">
<FontObject>
<foType>Título</foType>
<fontStyle>1</fontStyle>
<colorRGB>-16776961</colorRGB>
</FontObject>
<FontObject>
<foType>Columna</foType>
<colorRGB>-16777216</colorRGB>
</FontObject>
<FontObject>
<foType>Tipo de Dato</foType>
<colorRGB>-16744448</colorRGB>
</FontObject>
<FontObject>
<foType>Elemento de Clave Primaria</foType>
<colorRGB>-16776961</colorRGB>
</FontObject>
<FontObject>
<foType>Elemento de Clave Ajena</foType>
<colorRGB>-16777216</colorRGB>
</FontObject>
<FontObject>
<foType>Elemento de Clave Única</foType>
<colorRGB>-16776961</colorRGB>
</FontObject>
<FontObject>
<foType>No Nulo</foType>
<colorRGB>-65536</colorRGB>
</FontObject>
<FontObject>
<foType>Clave</foType>
<colorRGB>-16777216</colorRGB>
</FontObject>
<FontObject>
<foType>Comentarios</foType>
<colorRGB>-12566464</colorRGB>
</FontObject>
</fonts>
</OView>
<OView class="oracle.dbtools.crest.swingui.relational.TVTable" oid="1329C2F2-7947-560F-349D-6B873EB9BCC2" otype="Table" vid="C81CA3FE-2855-05A6-BE0A-646DB067E5AD">
<hideElementsInCurrentOnly>false</hideElementsInCurrentOnly>
<bounds x="83" y="3624" width="239" height="147"/>
<useCustomFormat>true</useCustomFormat>
<useDefaultColor>false</useDefaultColor>
<backgroundColor>-3355648</backgroundColor>
<foregroundColor>-16776961</foregroundColor>
<fonts itemClass="oracle.dbtools.crest.model.design.FontObjectWr">
<FontObject>
<foType>Título</foType>
<fontStyle>1</fontStyle>
<colorRGB>-16776961</colorRGB>
</FontObject>
<FontObject>
<foType>Columna</foType>
<colorRGB>-16777216</colorRGB>
</FontObject>
<FontObject>
<foType>Tipo de Dato</foType>
<colorRGB>-16744448</colorRGB>
</FontObject>
<FontObject>
<foType>Elemento de Clave Primaria</foType>
<colorRGB>-16776961</colorRGB>
</FontObject>
<FontObject>
<foType>Elemento de Clave Ajena</foType>
<colorRGB>-16777216</colorRGB>
</FontObject>
<FontObject>
<foType>Elemento de Clave Única</foType>
<colorRGB>-16776961</colorRGB>
</FontObject>
<FontObject>
<foType>No Nulo</foType>
<colorRGB>-65536</colorRGB>
</FontObject>
<FontObject>
<foType>Clave</foType>
<colorRGB>-16777216</colorRGB>
</FontObject>
<FontObject>
<foType>Comentarios</foType>
<colorRGB>-12566464</colorRGB>
</FontObject>
</fonts>
</OView>
<OView class="oracle.dbtools.crest.swingui.relational.TVTable" oid="16EED50C-31BE-AD9E-58C2-703B5944911A" otype="Table" vid="E9403B8B-FC88-2658-E7B1-D4BCEC1785B1">
<hideElementsInCurrentOnly>false</hideElementsInCurrentOnly>
<bounds x="1169" y="2643" width="291" height="325"/>
<useCustomFormat>true</useCustomFormat>
<useDefaultColor>false</useDefaultColor>
<backgroundColor>-26215</backgroundColor>
<foregroundColor>-16776961</foregroundColor>
<fonts itemClass="oracle.dbtools.crest.model.design.FontObjectWr">
<FontObject>
<foType>Título</foType>
<fontStyle>1</fontStyle>
<colorRGB>-16776961</colorRGB>
</FontObject>
<FontObject>
<foType>Columna</foType>
<colorRGB>-16777216</colorRGB>
</FontObject>
<FontObject>
<foType>Tipo de Dato</foType>
<colorRGB>-16744448</colorRGB>
</FontObject>
<FontObject>
<foType>Elemento de Clave Primaria</foType>
<colorRGB>-16776961</colorRGB>
</FontObject>
<FontObject>
<foType>Elemento de Clave Ajena</foType>
<colorRGB>-16777216</colorRGB>
</FontObject>
<FontObject>
<foType>Elemento de Clave Única</foType>
<colorRGB>-16776961</colorRGB>
</FontObject>
<FontObject>
<foType>No Nulo</foType>
<colorRGB>-65536</colorRGB>
</FontObject>
<FontObject>
<foType>Clave</foType>
<colorRGB>-16777216</colorRGB>
</FontObject>
<FontObject>
<foType>Comentarios</foType>
<colorRGB>-12566464</colorRGB>
</FontObject>
</fonts>
</OView>
<OView class="oracle.dbtools.crest.swingui.relational.TVTable" oid="1D441F17-9E2A-65AE-AACB-1816D3F8BD46" otype="Table" vid="1556EB60-D600-CE34-0C18-AFC6D16A0B8B">
<hideElementsInCurrentOnly>false</hideElementsInCurrentOnly>
<bounds x="51" y="245" width="244" height="238"/>
<useCustomFormat>true</useCustomFormat>
<useDefaultColor>false</useDefaultColor>
<backgroundColor>-103</backgroundColor>
<foregroundColor>-16776961</foregroundColor>
<fonts itemClass="oracle.dbtools.crest.model.design.FontObjectWr">
<FontObject>
<foType>Título</foType>
<fontStyle>1</fontStyle>
<colorRGB>-16776961</colorRGB>
</FontObject>
<FontObject>
<foType>Columna</foType>
<colorRGB>-16777216</colorRGB>
</FontObject>
<FontObject>
<foType>Tipo de Dato</foType>
<colorRGB>-16744448</colorRGB>
</FontObject>
<FontObject>
<foType>Elemento de Clave Primaria</foType>
<colorRGB>-16776961</colorRGB>
</FontObject>
<FontObject>
<foType>Elemento de Clave Ajena</foType>
<colorRGB>-16777216</colorRGB>
</FontObject>
<FontObject>
<foType>Elemento de Clave Única</foType>
<colorRGB>-16776961</colorRGB>
</FontObject>
<FontObject>
<foType>No Nulo</foType>
<colorRGB>-65536</colorRGB>
</FontObject>
<FontObject>
<foType>Clave</foType>
<colorRGB>-16777216</colorRGB>
</FontObject>
<FontObject>
<foType>Comentarios</foType>
<colorRGB>-12566464</colorRGB>
</FontObject>
</fonts>
</OView>
<OView class="oracle.dbtools.crest.swingui.relational.TVTable" oid="2062EDF6-E0BE-2E70-B1F9-CDF5B24D88E7" otype="Table" vid="A0CA09EB-7EA2-11D2-08C3-0185632F2D6D">
<hideElementsInCurrentOnly>false</hideElementsInCurrentOnly>
<bounds x="844" y="3415" width="330" height="306"/>
<useCustomFormat>true</useCustomFormat>
<useDefaultColor>false</useDefaultColor>
<backgroundColor>-3355648</backgroundColor>
<foregroundColor>-16776961</foregroundColor>
<fonts itemClass="oracle.dbtools.crest.model.design.FontObjectWr">
<FontObject>
<foType>Título</foType>
<fontStyle>1</fontStyle>
<colorRGB>-16776961</colorRGB>
</FontObject>
<FontObject>
<foType>Columna</foType>
<colorRGB>-16777216</colorRGB>
</FontObject>
<FontObject>
<foType>Tipo de Dato</foType>
<colorRGB>-16744448</colorRGB>
</FontObject>
<FontObject>
<foType>Elemento de Clave Primaria</foType>
<colorRGB>-16776961</colorRGB>
</FontObject>
<FontObject>
<foType>Elemento de Clave Ajena</foType>
<colorRGB>-16777216</colorRGB>
</FontObject>
<FontObject>
<foType>Elemento de Clave Única</foType>
<colorRGB>-16776961</colorRGB>
</FontObject>
<FontObject>
<foType>No Nulo</foType>
<colorRGB>-65536</colorRGB>
</FontObject>
<FontObject>
<foType>Clave</foType>
<colorRGB>-16777216</colorRGB>
</FontObject>
<FontObject>
<foType>Comentarios</foType>
<colorRGB>-12566464</colorRGB>
</FontObject>
</fonts>
</OView>
<OView class="oracle.dbtools.crest.swingui.relational.TVTable" oid="20EBC5C2-8E09-E7D7-D1AB-005FF5AA9550" otype="Table" vid="519947E2-CCFF-C6C5-9BD9-21ABA51A1DDC">
<hideElementsInCurrentOnly>false</hideElementsInCurrentOnly>
<bounds x="68" y="3386" width="389" height="207"/>
<useCustomFormat>true</useCustomFormat>
<useDefaultColor>false</useDefaultColor>
<backgroundColor>-3355648</backgroundColor>
<foregroundColor>-16776961</foregroundColor>
<fonts itemClass="oracle.dbtools.crest.model.design.FontObjectWr">
<FontObject>
<foType>Título</foType>
<fontStyle>1</fontStyle>
<colorRGB>-16776961</colorRGB>
</FontObject>
<FontObject>
<foType>Columna</foType>
<colorRGB>-16777216</colorRGB>
</FontObject>
<FontObject>
<foType>Tipo de Dato</foType>
<colorRGB>-16744448</colorRGB>
</FontObject>
<FontObject>
<foType>Elemento de Clave Primaria</foType>
<colorRGB>-16776961</colorRGB>
</FontObject>
<FontObject>
<foType>Elemento de Clave Ajena</foType>
<colorRGB>-16777216</colorRGB>
</FontObject>
<FontObject>
<foType>Elemento de Clave Única</foType>
<colorRGB>-16776961</colorRGB>
</FontObject>
<FontObject>
<foType>No Nulo</foType>
<colorRGB>-65536</colorRGB>
</FontObject>
<FontObject>
<foType>Clave</foType>
<colorRGB>-16777216</colorRGB>
</FontObject>
<FontObject>
<foType>Comentarios</foType>
<colorRGB>-12566464</colorRGB>
</FontObject>
</fonts>
</OView>
<OView class="oracle.dbtools.crest.swingui.relational.TVTable" oid="43226E34-D62B-CAA9-4851-4A90B120B81C" otype="Table" vid="3AA50766-6FFB-A4E1-E8DF-E3A6E829D3BE">
<hideElementsInCurrentOnly>false</hideElementsInCurrentOnly>
<bounds x="48" y="11" width="389" height="206"/>
<useCustomFormat>true</useCustomFormat>
<useDefaultColor>false</useDefaultColor>
<backgroundColor>-103</backgroundColor>
<foregroundColor>-16776961</foregroundColor>
<fonts itemClass="oracle.dbtools.crest.model.design.FontObjectWr">
<FontObject>
<foType>Título</foType>
<fontStyle>1</fontStyle>
<colorRGB>-16776961</colorRGB>
</FontObject>
<FontObject>
<foType>Columna</foType>
<colorRGB>-16777216</colorRGB>
</FontObject>
<FontObject>
<foType>Tipo de Dato</foType>
<colorRGB>-16744448</colorRGB>
</FontObject>
<FontObject>
<foType>Elemento de Clave Primaria</foType>
<colorRGB>-16776961</colorRGB>
</FontObject>
<FontObject>
<foType>Elemento de Clave Ajena</foType>
<colorRGB>-16777216</colorRGB>
</FontObject>
<FontObject>
<foType>Elemento de Clave Única</foType>
<colorRGB>-16776961</colorRGB>
</FontObject>
<FontObject>
<foType>No Nulo</foType>
<colorRGB>-65536</colorRGB>
</FontObject>
<FontObject>
<foType>Clave</foType>
<colorRGB>-16777216</colorRGB>
</FontObject>
<FontObject>
<foType>Comentarios</foType>
<colorRGB>-12566464</colorRGB>
</FontObject>
</fonts>
</OView>
<OView class="oracle.dbtools.crest.swingui.relational.TVTable" oid="56F15EC0-5A53-CD81-0FDF-AC8350B48DF7" otype="Table" vid="A02771A7-2D03-6A09-9554-98CE993CCF16">
<hideElementsInCurrentOnly>false</hideElementsInCurrentOnly>
<bounds x="327" y="1037" width="239" height="146"/>
<useCustomFormat>true</useCustomFormat>
<useDefaultColor>false</useDefaultColor>
<backgroundColor>-6697729</backgroundColor>
<foregroundColor>-16776961</foregroundColor>
<fonts itemClass="oracle.dbtools.crest.model.design.FontObjectWr">
<FontObject>
<foType>Título</foType>
<fontStyle>1</fontStyle>
<colorRGB>-16776961</colorRGB>
</FontObject>
<FontObject>
<foType>Columna</foType>
<colorRGB>-16777216</colorRGB>
</FontObject>
<FontObject>
<foType>Tipo de Dato</foType>
<colorRGB>-16744448</colorRGB>
</FontObject>
<FontObject>
<foType>Elemento de Clave Primaria</foType>
<colorRGB>-16776961</colorRGB>
</FontObject>
<FontObject>
<foType>Elemento de Clave Ajena</foType>
<colorRGB>-16777216</colorRGB>
</FontObject>
<FontObject>
<foType>Elemento de Clave Única</foType>
<colorRGB>-16776961</colorRGB>
</FontObject>
<FontObject>
<foType>No Nulo</foType>
<colorRGB>-65536</colorRGB>
</FontObject>
<FontObject>
<foType>Clave</foType>
<colorRGB>-16777216</colorRGB>
</FontObject>
<FontObject>
<foType>Comentarios</foType>
<colorRGB>-12566464</colorRGB>
</FontObject>
</fonts>
</OView>
<OView class="oracle.dbtools.crest.swingui.relational.TVTable" oid="5B869CDC-50E0-9269-06FD-81F88DAA9169" otype="Table" vid="D8DB1191-9A7D-3290-3975-23CCE8440771">
<hideElementsInCurrentOnly>false</hideElementsInCurrentOnly>
<bounds x="376" y="3729" width="257" height="178"/>
<useCustomFormat>true</useCustomFormat>
<useDefaultColor>false</useDefaultColor>
<backgroundColor>-3355648</backgroundColor>
<foregroundColor>-16776961</foregroundColor>
<fonts itemClass="oracle.dbtools.crest.model.design.FontObjectWr">
<FontObject>
<foType>Título</foType>
<fontStyle>1</fontStyle>
<colorRGB>-16776961</colorRGB>
</FontObject>
<FontObject>
<foType>Columna</foType>
<colorRGB>-16777216</colorRGB>
</FontObject>
<FontObject>
<foType>Tipo de Dato</foType>
<colorRGB>-16744448</colorRGB>
</FontObject>
<FontObject>
<foType>Elemento de Clave Primaria</foType>
<colorRGB>-16776961</colorRGB>
</FontObject>
<FontObject>
<foType>Elemento de Clave Ajena</foType>
<colorRGB>-16777216</colorRGB>
</FontObject>
<FontObject>
<foType>Elemento de Clave Única</foType>
<colorRGB>-16776961</colorRGB>
</FontObject>
<FontObject>
<foType>No Nulo</foType>
<colorRGB>-65536</colorRGB>
</FontObject>
<FontObject>
<foType>Clave</foType>
<colorRGB>-16777216</colorRGB>
</FontObject>
<FontObject>
<foType>Comentarios</foType>
<colorRGB>-12566464</colorRGB>
</FontObject>
</fonts>
</OView>
<OView class="oracle.dbtools.crest.swingui.relational.TVTable" oid="65FE206B-0B8B-8BEA-B401-9A89C5E78A03" otype="Table" vid="D62E5757-C93C-AFB6-3CCE-93ABE6CE05FE">
<hideElementsInCurrentOnly>false</hideElementsInCurrentOnly>
<bounds x="436" y="1600" width="271" height="162"/>
</OView>
<OView class="oracle.dbtools.crest.swingui.relational.TVTable" oid="79FC249F-65F3-E4E7-C514-F142C10E451E" otype="Table" vid="E5FD6586-A1AA-25B1-6EF9-84E308972405">
<hideElementsInCurrentOnly>false</hideElementsInCurrentOnly>
<bounds x="22" y="2272" width="294" height="440"/>
<useCustomFormat>true</useCustomFormat>
<useDefaultColor>false</useDefaultColor>
<backgroundColor>-26215</backgroundColor>
<foregroundColor>-16776961</foregroundColor>
<fonts itemClass="oracle.dbtools.crest.model.design.FontObjectWr">
<FontObject>
<foType>Título</foType>
<fontStyle>1</fontStyle>
<colorRGB>-16776961</colorRGB>
</FontObject>
<FontObject>
<foType>Columna</foType>
<colorRGB>-16777216</colorRGB>
</FontObject>
<FontObject>
<foType>Tipo de Dato</foType>
<colorRGB>-16744448</colorRGB>
</FontObject>
<FontObject>
<foType>Elemento de Clave Primaria</foType>
<colorRGB>-16776961</colorRGB>
</FontObject>
<FontObject>
<foType>Elemento de Clave Ajena</foType>
<colorRGB>-16777216</colorRGB>
</FontObject>
<FontObject>
<foType>Elemento de Clave Única</foType>
<colorRGB>-16776961</colorRGB>
</FontObject>
<FontObject>
<foType>No Nulo</foType>
<colorRGB>-65536</colorRGB>
</FontObject>
<FontObject>
<foType>Clave</foType>
<colorRGB>-16777216</colorRGB>
</FontObject>
<FontObject>
<foType>Comentarios</foType>
<colorRGB>-12566464</colorRGB>
</FontObject>
</fonts>
</OView>
<OView class="oracle.dbtools.crest.swingui.relational.TVTable" oid="7BC3347B-B4B5-D1E2-A4CD-74A2092B3332" otype="Table" vid="2DC07648-8D7C-E554-BA42-42AB4DE90B75">
<hideElementsInCurrentOnly>false</hideElementsInCurrentOnly>
<bounds x="1171" y="2979" width="291" height="262"/>
<useCustomFormat>true</useCustomFormat>
<useDefaultColor>false</useDefaultColor>
<backgroundColor>-26215</backgroundColor>
<foregroundColor>-16776961</foregroundColor>
<fonts itemClass="oracle.dbtools.crest.model.design.FontObjectWr">
<FontObject>
<foType>Título</foType>
<fontStyle>1</fontStyle>
<colorRGB>-16776961</colorRGB>
</FontObject>
<FontObject>
<foType>Columna</foType>
<colorRGB>-16777216</colorRGB>
</FontObject>
<FontObject>
<foType>Tipo de Dato</foType>
<colorRGB>-16744448</colorRGB>
</FontObject>
<FontObject>
<foType>Elemento de Clave Primaria</foType>
<colorRGB>-16776961</colorRGB>
</FontObject>
<FontObject>
<foType>Elemento de Clave Ajena</foType>
<colorRGB>-16777216</colorRGB>
</FontObject>
<FontObject>
<foType>Elemento de Clave Única</foType>
<colorRGB>-16776961</colorRGB>
</FontObject>
<FontObject>
<foType>No Nulo</foType>
<colorRGB>-65536</colorRGB>
</FontObject>
<FontObject>
<foType>Clave</foType>
<colorRGB>-16777216</colorRGB>
</FontObject>
<FontObject>
<foType>Comentarios</foType>
<colorRGB>-12566464</colorRGB>
</FontObject>
</fonts>
</OView>
<OView class="oracle.dbtools.crest.swingui.relational.TVTable" oid="84046119-2247-A8DB-AB03-C7C6347ADBB8" otype="Table" vid="222C2E04-E480-F583-B543-A5D5A041EAB2">
<hideElementsInCurrentOnly>false</hideElementsInCurrentOnly>
<bounds x="26" y="2044" width="296" height="204"/>
<useCustomFormat>true</useCustomFormat>
<useDefaultColor>false</useDefaultColor>
<backgroundColor>-13369345</backgroundColor>
<foregroundColor>-16776961</foregroundColor>
<fonts itemClass="oracle.dbtools.crest.model.design.FontObjectWr">
<FontObject>
<foType>Título</foType>
<fontStyle>1</fontStyle>
<colorRGB>-16776961</colorRGB>
</FontObject>
<FontObject>
<foType>Columna</foType>
<colorRGB>-16777216</colorRGB>
</FontObject>
<FontObject>
<foType>Tipo de Dato</foType>
<colorRGB>-16744448</colorRGB>
</FontObject>
<FontObject>
<foType>Elemento de Clave Primaria</foType>
<colorRGB>-16776961</colorRGB>
</FontObject>
<FontObject>
<foType>Elemento de Clave Ajena</foType>
<colorRGB>-16777216</colorRGB>
</FontObject>
<FontObject>
<foType>Elemento de Clave Única</foType>
<colorRGB>-16776961</colorRGB>
</FontObject>
<FontObject>
<foType>No Nulo</foType>
<colorRGB>-65536</colorRGB>
</FontObject>
<FontObject>
<foType>Clave</foType>
<colorRGB>-16777216</colorRGB>
</FontObject>
<FontObject>
<foType>Comentarios</foType>
<colorRGB>-12566464</colorRGB>
</FontObject>
</fonts>
</OView>
<OView class="oracle.dbtools.crest.swingui.relational.TVTable" oid="8BFF8C5A-0611-5230-ADAE-D7F61617036A" otype="Table" vid="2E1B75AD-C284-E847-3D1A-9A84160DAE37">
<hideElementsInCurrentOnly>false</hideElementsInCurrentOnly>
<bounds x="433" y="2080" width="256" height="145"/>
<useCustomFormat>true</useCustomFormat>
<useDefaultColor>false</useDefaultColor>
<backgroundColor>-13369345</backgroundColor>
<foregroundColor>-16776961</foregroundColor>
<fonts itemClass="oracle.dbtools.crest.model.design.FontObjectWr">
<FontObject>
<foType>Título</foType>
<fontStyle>1</fontStyle>
<colorRGB>-16776961</colorRGB>
</FontObject>
<FontObject>
<foType>Columna</foType>
<colorRGB>-16777216</colorRGB>
</FontObject>
<FontObject>
<foType>Tipo de Dato</foType>
<colorRGB>-16744448</colorRGB>
</FontObject>
<FontObject>
<foType>Elemento de Clave Primaria</foType>
<colorRGB>-16776961</colorRGB>
</FontObject>
<FontObject>
<foType>Elemento de Clave Ajena</foType>
<colorRGB>-16777216</colorRGB>
</FontObject>
<FontObject>
<foType>Elemento de Clave Única</foType>
<colorRGB>-16776961</colorRGB>
</FontObject>
<FontObject>
<foType>No Nulo</foType>
<colorRGB>-65536</colorRGB>
</FontObject>
<FontObject>
<foType>Clave</foType>
<colorRGB>-16777216</colorRGB>
</FontObject>
<FontObject>
<foType>Comentarios</foType>
<colorRGB>-12566464</colorRGB>
</FontObject>
</fonts>
</OView>
<OView class="oracle.dbtools.crest.swingui.relational.TVTable" oid="8CF3CF4E-FC38-9016-8168-6FB6626231D7" otype="Table" vid="AAB0978E-5B29-0A94-12BF-62F1216DAE21">
<hideElementsInCurrentOnly>false</hideElementsInCurrentOnly>
<bounds x="784" y="2089" width="294" height="132"/>
<useCustomFormat>true</useCustomFormat>
<useDefaultColor>false</useDefaultColor>
<backgroundColor>-16711681</backgroundColor>
<foregroundColor>-16776961</foregroundColor>
<fonts itemClass="oracle.dbtools.crest.model.design.FontObjectWr">
<FontObject>
<foType>Título</foType>
<fontStyle>1</fontStyle>
<colorRGB>-16776961</colorRGB>
</FontObject>
<FontObject>
<foType>Columna</foType>
<colorRGB>-16777216</colorRGB>
</FontObject>
<FontObject>
<foType>Tipo de Dato</foType>
<colorRGB>-16744448</colorRGB>
</FontObject>
<FontObject>
<foType>Elemento de Clave Primaria</foType>
<colorRGB>-16776961</colorRGB>
</FontObject>
<FontObject>
<foType>Elemento de Clave Ajena</foType>
<colorRGB>-16777216</colorRGB>
</FontObject>
<FontObject>
<foType>Elemento de Clave Única</foType>
<colorRGB>-16776961</colorRGB>
</FontObject>
<FontObject>
<foType>No Nulo</foType>
<colorRGB>-65536</colorRGB>
</FontObject>
<FontObject>
<foType>Clave</foType>
<colorRGB>-16777216</colorRGB>
</FontObject>
<FontObject>
<foType>Comentarios</foType>
<colorRGB>-12566464</colorRGB>
</FontObject>
</fonts>
</OView>
<OView class="oracle.dbtools.crest.swingui.relational.TVTable" oid="929035AE-277F-3E87-9A17-A4B099975109" otype="Table" vid="86D867F0-B399-3746-0BA8-E4B0D1B4F281">
<hideElementsInCurrentOnly>false</hideElementsInCurrentOnly>
<bounds x="53" y="800" width="389" height="206"/>
<useCustomFormat>true</useCustomFormat>
<useDefaultColor>false</useDefaultColor>
<backgroundColor>-6697729</backgroundColor>
<foregroundColor>-16776961</foregroundColor>
<fonts itemClass="oracle.dbtools.crest.model.design.FontObjectWr">
<FontObject>
<foType>Título</foType>
<fontStyle>1</fontStyle>
<colorRGB>-16776961</colorRGB>
</FontObject>
<FontObject>
<foType>Columna</foType>
<colorRGB>-16777216</colorRGB>
</FontObject>
<FontObject>
<foType>Tipo de Dato</foType>
<colorRGB>-16744448</colorRGB>
</FontObject>
<FontObject>
<foType>Elemento de Clave Primaria</foType>
<colorRGB>-16776961</colorRGB>
</FontObject>
<FontObject>
<foType>Elemento de Clave Ajena</foType>
<colorRGB>-16777216</colorRGB>
</FontObject>
<FontObject>
<foType>Elemento de Clave Única</foType>
<colorRGB>-16776961</colorRGB>
</FontObject>
<FontObject>
<foType>No Nulo</foType>
<colorRGB>-65536</colorRGB>
</FontObject>
<FontObject>
<foType>Clave</foType>
<colorRGB>-16777216</colorRGB>
</FontObject>
<FontObject>
<foType>Comentarios</foType>
<colorRGB>-12566464</colorRGB>
</FontObject>
</fonts>
</OView>
<OView class="oracle.dbtools.crest.swingui.relational.TVTable" oid="981CCADE-6C2E-8BB6-4109-6CEE0313B367" otype="Table" vid="458FD6D9-9E22-ECF3-11A5-6EC0B8E2ED80">
<hideElementsInCurrentOnly>false</hideElementsInCurrentOnly>
<bounds x="319" y="245" width="239" height="145"/>
<useCustomFormat>true</useCustomFormat>
<useDefaultColor>false</useDefaultColor>
<backgroundColor>-103</backgroundColor>
<foregroundColor>-16776961</foregroundColor>
<fonts itemClass="oracle.dbtools.crest.model.design.FontObjectWr">
<FontObject>
<foType>Título</foType>
<fontStyle>1</fontStyle>
<colorRGB>-16776961</colorRGB>
</FontObject>
<FontObject>
<foType>Columna</foType>
<colorRGB>-16777216</colorRGB>
</FontObject>
<FontObject>
<foType>Tipo de Dato</foType>
<colorRGB>-16744448</colorRGB>
</FontObject>
<FontObject>
<foType>Elemento de Clave Primaria</foType>
<colorRGB>-16776961</colorRGB>
</FontObject>
<FontObject>
<foType>Elemento de Clave Ajena</foType>
<colorRGB>-16777216</colorRGB>
</FontObject>
<FontObject>
<foType>Elemento de Clave Única</foType>
<colorRGB>-16776961</colorRGB>
</FontObject>
<FontObject>
<foType>No Nulo</foType>
<colorRGB>-65536</colorRGB>
</FontObject>
<FontObject>
<foType>Clave</foType>
<colorRGB>-16777216</colorRGB>
</FontObject>
<FontObject>
<foType>Comentarios</foType>
<colorRGB>-12566464</colorRGB>
</FontObject>
</fonts>
</OView>
<OView class="oracle.dbtools.crest.swingui.relational.TVTable" oid="9D23544B-171E-42C8-1EDF-3798CEAAB002" otype="Table" vid="6AE22CF0-1D36-C9B8-8A18-8C1F36535FF2">
<hideElementsInCurrentOnly>false</hideElementsInCurrentOnly>
<bounds x="52" y="492" width="287" height="302"/>
<useCustomFormat>true</useCustomFormat>
<useDefaultColor>false</useDefaultColor>
<backgroundColor>-6684775</backgroundColor>
<foregroundColor>-16776961</foregroundColor>
<fonts itemClass="oracle.dbtools.crest.model.design.FontObjectWr">
<FontObject>
<foType>Título</foType>
<fontStyle>1</fontStyle>
<colorRGB>-16776961</colorRGB>
</FontObject>
<FontObject>
<foType>Columna</foType>
<colorRGB>-16777216</colorRGB>
</FontObject>
<FontObject>
<foType>Tipo de Dato</foType>
<colorRGB>-16744448</colorRGB>
</FontObject>
<FontObject>
<foType>Elemento de Clave Primaria</foType>
<colorRGB>-16776961</colorRGB>
</FontObject>
<FontObject>
<foType>Elemento de Clave Ajena</foType>
<colorRGB>-16777216</colorRGB>
</FontObject>
<FontObject>
<foType>Elemento de Clave Única</foType>
<colorRGB>-16776961</colorRGB>
</FontObject>
<FontObject>
<foType>No Nulo</foType>
<colorRGB>-65536</colorRGB>
</FontObject>
<FontObject>
<foType>Clave</foType>
<colorRGB>-16777216</colorRGB>
</FontObject>
<FontObject>
<foType>Comentarios</foType>
<colorRGB>-12566464</colorRGB>
</FontObject>
</fonts>
</OView>
<OView class="oracle.dbtools.crest.swingui.relational.TVTable" oid="A16BBD76-20C6-35C0-55B0-CCE1C09DE610" otype="Table" vid="6BA8A7B9-BEA5-E5EB-D20C-FEBA39FE8E4D">
<hideElementsInCurrentOnly>false</hideElementsInCurrentOnly>
<bounds x="52" y="1045" width="244" height="245"/>
<useCustomFormat>true</useCustomFormat>
<useDefaultColor>false</useDefaultColor>
<backgroundColor>-6697729</backgroundColor>
<foregroundColor>-16776961</foregroundColor>
<fonts itemClass="oracle.dbtools.crest.model.design.FontObjectWr">
<FontObject>
<foType>Título</foType>
<fontStyle>1</fontStyle>
<colorRGB>-16776961</colorRGB>
</FontObject>
<FontObject>
<foType>Columna</foType>
<colorRGB>-16777216</colorRGB>
</FontObject>
<FontObject>
<foType>Tipo de Dato</foType>
<colorRGB>-16744448</colorRGB>
</FontObject>
<FontObject>
<foType>Elemento de Clave Primaria</foType>
<colorRGB>-16776961</colorRGB>
</FontObject>
<FontObject>
<foType>Elemento de Clave Ajena</foType>
<colorRGB>-16777216</colorRGB>
</FontObject>
<FontObject>
<foType>Elemento de Clave Única</foType>
<colorRGB>-16776961</colorRGB>
</FontObject>
<FontObject>
<foType>No Nulo</foType>
<colorRGB>-65536</colorRGB>
</FontObject>
<FontObject>
<foType>Clave</foType>
<colorRGB>-16777216</colorRGB>
</FontObject>
<FontObject>
<foType>Comentarios</foType>
<colorRGB>-12566464</colorRGB>
</FontObject>
</fonts>
</OView>
<OView class="oracle.dbtools.crest.swingui.relational.TVTable" oid="A279984A-52DC-D790-2667-09A5E4465E57" otype="Table" vid="95E0A1BD-153B-C40F-C9A1-BB39C988D64E">
<hideElementsInCurrentOnly>false</hideElementsInCurrentOnly>
<bounds x="56" y="1310" width="384" height="194"/>
</OView>
<OView class="oracle.dbtools.crest.swingui.relational.TVTable" oid="A3A8F5FC-A198-F71E-6A84-4554734943CE" otype="Table" vid="FE4606E6-49C6-0BC6-A0A4-71CCAEC12487">
<hideElementsInCurrentOnly>false</hideElementsInCurrentOnly>
<bounds x="597" y="491" width="279" height="189"/>
<useCustomFormat>true</useCustomFormat>
<useDefaultColor>false</useDefaultColor>
<backgroundColor>-6684775</backgroundColor>
<foregroundColor>-16776961</foregroundColor>
<fonts itemClass="oracle.dbtools.crest.model.design.FontObjectWr">
<FontObject>
<foType>Título</foType>
<fontStyle>1</fontStyle>
<colorRGB>-16776961</colorRGB>
</FontObject>
<FontObject>
<foType>Columna</foType>
<colorRGB>-16777216</colorRGB>
</FontObject>
<FontObject>
<foType>Tipo de Dato</foType>
<colorRGB>-16744448</colorRGB>
</FontObject>
<FontObject>
<foType>Elemento de Clave Primaria</foType>
<colorRGB>-16776961</colorRGB>
</FontObject>
<FontObject>
<foType>Elemento de Clave Ajena</foType>
<colorRGB>-16777216</colorRGB>
</FontObject>
<FontObject>
<foType>Elemento de Clave Única</foType>
<colorRGB>-16776961</colorRGB>
</FontObject>
<FontObject>
<foType>No Nulo</foType>
<colorRGB>-65536</colorRGB>
</FontObject>
<FontObject>
<foType>Clave</foType>
<colorRGB>-16777216</colorRGB>
</FontObject>
<FontObject>
<foType>Comentarios</foType>
<colorRGB>-12566464</colorRGB>
</FontObject>
</fonts>
</OView>
<OView class="oracle.dbtools.crest.swingui.relational.TVTable" oid="A7618BE0-ACBC-A6B9-06DB-A776E7ECDBF3" otype="Table" vid="2B33AD59-8CF7-D06A-A7A8-8E64995EAC20">
<hideElementsInCurrentOnly>false</hideElementsInCurrentOnly>
<bounds x="760" y="1763" width="210" height="109"/>
</OView>
<OView class="oracle.dbtools.crest.swingui.relational.TVTable" oid="A92C846E-1EB4-EF31-DEA4-DE07D526943F" otype="Table" vid="EFF2A1D3-CD40-E505-8D9B-7C7B834CBA77">
<hideElementsInCurrentOnly>false</hideElementsInCurrentOnly>
<bounds x="24" y="3027" width="291" height="207"/>
<useCustomFormat>true</useCustomFormat>
<useDefaultColor>false</useDefaultColor>
<backgroundColor>-26215</backgroundColor>
<foregroundColor>-16776961</foregroundColor>
<fonts itemClass="oracle.dbtools.crest.model.design.FontObjectWr">
<FontObject>
<foType>Título</foType>
<fontStyle>1</fontStyle>
<colorRGB>-16776961</colorRGB>
</FontObject>
<FontObject>
<foType>Columna</foType>
<colorRGB>-16777216</colorRGB>
</FontObject>
<FontObject>
<foType>Tipo de Dato</foType>
<colorRGB>-16744448</colorRGB>
</FontObject>
<FontObject>
<foType>Elemento de Clave Primaria</foType>
<colorRGB>-16776961</colorRGB>
</FontObject>
<FontObject>
<foType>Elemento de Clave Ajena</foType>
<colorRGB>-16777216</colorRGB>
</FontObject>
<FontObject>
<foType>Elemento de Clave Única</foType>
<colorRGB>-16776961</colorRGB>
</FontObject>
<FontObject>
<foType>No Nulo</foType>
<colorRGB>-65536</colorRGB>
</FontObject>
<FontObject>
<foType>Clave</foType>
<colorRGB>-16777216</colorRGB>
</FontObject>
<FontObject>
<foType>Comentarios</foType>
<colorRGB>-12566464</colorRGB>
</FontObject>
</fonts>
</OView>
<OView class="oracle.dbtools.crest.swingui.relational.TVTable" oid="B3DB267D-E602-B718-40F4-B0113E263410" otype="Table" vid="44F86DCF-E5B2-EA44-7A0E-0D24BF874AA4">
<hideElementsInCurrentOnly>false</hideElementsInCurrentOnly>
<bounds x="595" y="13" width="330" height="305"/>
<useCustomFormat>true</useCustomFormat>
<useDefaultColor>false</useDefaultColor>
<backgroundColor>-103</backgroundColor>
<foregroundColor>-16776961</foregroundColor>
<fonts itemClass="oracle.dbtools.crest.model.design.FontObjectWr">
<FontObject>
<foType>Título</foType>
<fontStyle>1</fontStyle>
<colorRGB>-16776961</colorRGB>
</FontObject>
<FontObject>
<foType>Columna</foType>
<colorRGB>-16777216</colorRGB>
</FontObject>
<FontObject>
<foType>Tipo de Dato</foType>
<colorRGB>-16744448</colorRGB>
</FontObject>
<FontObject>
<foType>Elemento de Clave Primaria</foType>
<colorRGB>-16776961</colorRGB>
</FontObject>
<FontObject>
<foType>Elemento de Clave Ajena</foType>
<colorRGB>-16777216</colorRGB>
</FontObject>
<FontObject>
<foType>Elemento de Clave Única</foType>
<colorRGB>-16776961</colorRGB>
</FontObject>
<FontObject>
<foType>No Nulo</foType>
<colorRGB>-65536</colorRGB>
</FontObject>
<FontObject>
<foType>Clave</foType>
<colorRGB>-16777216</colorRGB>
</FontObject>
<FontObject>
<foType>Comentarios</foType>
<colorRGB>-12566464</colorRGB>
</FontObject>
</fonts>
</OView>
<OView class="oracle.dbtools.crest.swingui.relational.TVTable" oid="BA2D9312-2078-3B0A-CCA9-4B550C760F5C" otype="Table" vid="8179925D-9702-2C75-5546-6ED5040DE8FD">
<hideElementsInCurrentOnly>false</hideElementsInCurrentOnly>
<bounds x="603" y="796" width="330" height="305"/>
<useCustomFormat>true</useCustomFormat>
<useDefaultColor>false</useDefaultColor>
<backgroundColor>-6697729</backgroundColor>
<foregroundColor>-16776961</foregroundColor>
<fonts itemClass="oracle.dbtools.crest.model.design.FontObjectWr">
<FontObject>
<foType>Título</foType>
<fontStyle>1</fontStyle>
<colorRGB>-16776961</colorRGB>
</FontObject>
<FontObject>
<foType>Columna</foType>
<colorRGB>-16777216</colorRGB>
</FontObject>
<FontObject>
<foType>Tipo de Dato</foType>
<colorRGB>-16744448</colorRGB>
</FontObject>
<FontObject>
<foType>Elemento de Clave Primaria</foType>
<colorRGB>-16776961</colorRGB>
</FontObject>
<FontObject>
<foType>Elemento de Clave Ajena</foType>
<colorRGB>-16777216</colorRGB>
</FontObject>
<FontObject>
<foType>Elemento de Clave Única</foType>
<colorRGB>-16776961</colorRGB>
</FontObject>
<FontObject>
<foType>No Nulo</foType>
<colorRGB>-65536</colorRGB>
</FontObject>
<FontObject>
<foType>Clave</foType>
<colorRGB>-16777216</colorRGB>
</FontObject>
<FontObject>
<foType>Comentarios</foType>
<colorRGB>-12566464</colorRGB>
</FontObject>
</fonts>
</OView>
<OView class="oracle.dbtools.crest.swingui.relational.TVTable" oid="BA7A9598-6656-6F71-4BCC-09B97D226E90" otype="Table" vid="F65C957E-E336-C738-C965-DE4DFD522C26">
<hideElementsInCurrentOnly>false</hideElementsInCurrentOnly>
<bounds x="552" y="3482" width="257" height="173"/>
<useCustomFormat>true</useCustomFormat>
<useDefaultColor>false</useDefaultColor>
<backgroundColor>-3355648</backgroundColor>
<foregroundColor>-16776961</foregroundColor>
<fonts itemClass="oracle.dbtools.crest.model.design.FontObjectWr">
<FontObject>
<foType>Título</foType>
<fontStyle>1</fontStyle>
<colorRGB>-16776961</colorRGB>
</FontObject>
<FontObject>
<foType>Columna</foType>
<colorRGB>-16777216</colorRGB>
</FontObject>
<FontObject>
<foType>Tipo de Dato</foType>
<colorRGB>-16744448</colorRGB>
</FontObject>
<FontObject>
<foType>Elemento de Clave Primaria</foType>
<colorRGB>-16776961</colorRGB>
</FontObject>
<FontObject>
<foType>Elemento de Clave Ajena</foType>
<colorRGB>-16777216</colorRGB>
</FontObject>
<FontObject>
<foType>Elemento de Clave Única</foType>
<colorRGB>-16776961</colorRGB>
</FontObject>
<FontObject>
<foType>No Nulo</foType>
<colorRGB>-65536</colorRGB>
</FontObject>
<FontObject>
<foType>Clave</foType>
<colorRGB>-16777216</colorRGB>
</FontObject>
<FontObject>
<foType>Comentarios</foType>
<colorRGB>-12566464</colorRGB>
</FontObject>
</fonts>
</OView>
<OView class="oracle.dbtools.crest.swingui.relational.TVTable" oid="BE95B857-5538-36D6-8DA3-E48E353EB87C" otype="Table" vid="33B01EE8-01ED-5E0A-67EA-63067999A2A2">
<hideElementsInCurrentOnly>false</hideElementsInCurrentOnly>
<bounds x="65" y="1560" width="282" height="242"/>
</OView>
<OView class="oracle.dbtools.crest.swingui.relational.TVTable" oid="D29870D4-B328-DB58-78A0-DD8A2F5B00DD" otype="Table" vid="C2C8CB38-93EA-AB83-C419-B4134D9A157F">
<hideElementsInCurrentOnly>false</hideElementsInCurrentOnly>
<bounds x="1169" y="2269" width="291" height="364"/>
<useCustomFormat>true</useCustomFormat>
<useDefaultColor>false</useDefaultColor>
<backgroundColor>-26215</backgroundColor>
<foregroundColor>-16776961</foregroundColor>
<fonts itemClass="oracle.dbtools.crest.model.design.FontObjectWr">
<FontObject>
<foType>Título</foType>
<fontStyle>1</fontStyle>
<colorRGB>-16776961</colorRGB>
</FontObject>
<FontObject>
<foType>Columna</foType>
<colorRGB>-16777216</colorRGB>
</FontObject>
<FontObject>
<foType>Tipo de Dato</foType>
<colorRGB>-16744448</colorRGB>
</FontObject>
<FontObject>
<foType>Elemento de Clave Primaria</foType>
<colorRGB>-16776961</colorRGB>
</FontObject>
<FontObject>
<foType>Elemento de Clave Ajena</foType>
<colorRGB>-16777216</colorRGB>
</FontObject>
<FontObject>
<foType>Elemento de Clave Única</foType>
<colorRGB>-16776961</colorRGB>
</FontObject>
<FontObject>
<foType>No Nulo</foType>
<colorRGB>-65536</colorRGB>
</FontObject>
<FontObject>
<foType>Clave</foType>
<colorRGB>-16777216</colorRGB>
</FontObject>
<FontObject>
<foType>Comentarios</foType>
<colorRGB>-12566464</colorRGB>
</FontObject>
</fonts>
</OView>
<OView class="oracle.dbtools.crest.swingui.relational.TVTable" oid="D764DDD6-DD5A-7151-7721-B901BCE14B46" otype="Table" vid="AD54D755-D232-7CB4-FE77-D391461564CE">
<hideElementsInCurrentOnly>false</hideElementsInCurrentOnly>
<bounds x="805" y="1302" width="297" height="328"/>
</OView>
<OView class="oracle.dbtools.crest.swingui.relational.TVTable" oid="DE15921A-69CC-28B0-8D06-135DD1AD3248" otype="Table" vid="4C7135C7-9CE3-54B3-3ACD-4FF6EB25F8E3">
<hideElementsInCurrentOnly>false</hideElementsInCurrentOnly>
<bounds x="801" y="2270" width="341" height="924"/>
<useCustomFormat>true</useCustomFormat>
<useDefaultColor>false</useDefaultColor>
<backgroundColor>-26215</backgroundColor>
<foregroundColor>-16776961</foregroundColor>
<fonts itemClass="oracle.dbtools.crest.model.design.FontObjectWr">
<FontObject>
<foType>Título</foType>
<fontStyle>1</fontStyle>
<colorRGB>-16777216</colorRGB>
</FontObject>
<FontObject>
<foType>Columna</foType>
<colorRGB>-16777216</colorRGB>
</FontObject>
<FontObject>
<foType>Tipo de Dato</foType>
<colorRGB>-16744448</colorRGB>
</FontObject>
<FontObject>
<foType>Elemento de Clave Primaria</foType>
<colorRGB>-16776961</colorRGB>
</FontObject>
<FontObject>
<foType>Elemento de Clave Ajena</foType>
<colorRGB>-16777216</colorRGB>
</FontObject>
<FontObject>
<foType>Elemento de Clave Única</foType>
<colorRGB>-16776961</colorRGB>
</FontObject>
<FontObject>
<foType>No Nulo</foType>
<colorRGB>-65536</colorRGB>
</FontObject>
<FontObject>
<foType>Clave</foType>
<colorRGB>-16777216</colorRGB>
</FontObject>
<FontObject>
<foType>Comentarios</foType>
<colorRGB>-12566464</colorRGB>
</FontObject>
</fonts>
</OView>
<OView class="oracle.dbtools.crest.swingui.relational.TVTable" oid="E485EF67-6A3D-48BF-140C-2731F1E148FF" otype="Table" vid="60BCDDB9-D105-CD3E-BE62-D7F69DC8E87A">
<hideElementsInCurrentOnly>false</hideElementsInCurrentOnly>
<bounds x="485" y="1364" width="277" height="142"/>
</OView>
<OView class="oracle.dbtools.crest.swingui.relational.TVTable" oid="F0E12EBD-80F8-23A9-9C59-4D0BB32FDEE0" otype="Table" vid="17332F65-FED9-0117-4AED-E3EED97A9A7E">
<hideElementsInCurrentOnly>false</hideElementsInCurrentOnly>
<bounds x="414" y="3029" width="340" height="240"/>
<useCustomFormat>true</useCustomFormat>
<useDefaultColor>false</useDefaultColor>
<backgroundColor>-26215</backgroundColor>
<foregroundColor>-16776961</foregroundColor>
<fonts itemClass="oracle.dbtools.crest.model.design.FontObjectWr">
<FontObject>
<foType>Título</foType>
<fontStyle>1</fontStyle>
<colorRGB>-16776961</colorRGB>
</FontObject>
<FontObject>
<foType>Columna</foType>
<colorRGB>-16777216</colorRGB>
</FontObject>
<FontObject>
<foType>Tipo de Dato</foType>
<colorRGB>-16744448</colorRGB>
</FontObject>
<FontObject>
<foType>Elemento de Clave Primaria</foType>
<colorRGB>-16776961</colorRGB>
</FontObject>
<FontObject>
<foType>Elemento de Clave Ajena</foType>
<colorRGB>-16777216</colorRGB>
</FontObject>
<FontObject>
<foType>Elemento de Clave Única</foType>
<colorRGB>-16776961</colorRGB>
</FontObject>
<FontObject>
<foType>No Nulo</foType>
<colorRGB>-65536</colorRGB>
</FontObject>
<FontObject>
<foType>Clave</foType>
<colorRGB>-16777216</colorRGB>
</FontObject>
<FontObject>
<foType>Comentarios</foType>
<colorRGB>-12566464</colorRGB>
</FontObject>
</fonts>
</OView>
<OView class="oracle.dbtools.crest.swingui.relational.TVTable" oid="FD51D5A0-C6D5-86CD-6600-4A7903526F34" otype="Table" vid="D90F2EF2-D878-4ED8-A38C-F0C41C790B9E">
<hideElementsInCurrentOnly>false</hideElementsInCurrentOnly>
<bounds x="336" y="1885" width="270" height="154"/>
</OView>
</objectViews>
<connectors>
<Connector class="oracle.dbtools.crest.swingui.relational.TVFKRelation" oid="06C92587-382C-BA60-64EC-046EF46ECEBD" otype="FKIndexAssociation" vid_source="519947E2-CCFF-C6C5-9BD9-21ABA51A1DDC" vid_target="D8DB1191-9A7D-3290-3975-23CCE8440771">
<hideElementsInCurrentOnly>false</hideElementsInCurrentOnly>
<backgroundColor>-16777216</backgroundColor>
<lineWidth>1</lineWidth>
<points>
<point x="416" y="3593"/>
<point x="416" y="3729"/>
</points>
</Connector>
<Connector class="oracle.dbtools.crest.swingui.relational.TVFKRelation" oid="24E5CCBD-2751-9439-1C7F-79FE39101FEB" otype="FKIndexAssociation" vid_source="86D867F0-B399-3746-0BA8-E4B0D1B4F281" vid_target="6BA8A7B9-BEA5-E5EB-D20C-FEBA39FE8E4D">
<hideElementsInCurrentOnly>false</hideElementsInCurrentOnly>
<backgroundColor>-16777216</backgroundColor>
<lineWidth>1</lineWidth>
<points>
<point x="174" y="1006"/>
<point x="174" y="1045"/>
</points>
</Connector>
<Connector class="oracle.dbtools.crest.swingui.relational.TVFKRelation" oid="52225F6D-B5DE-56AF-25DA-D695E4E591AB" otype="FKIndexAssociation" vid_source="95E0A1BD-153B-C40F-C9A1-BB39C988D64E" vid_target="33B01EE8-01ED-5E0A-67EA-63067999A2A2">
<hideElementsInCurrentOnly>false</hideElementsInCurrentOnly>
<backgroundColor>-16777216</backgroundColor>
<lineWidth>1</lineWidth>
<points>
<point x="206" y="1504"/>
<point x="206" y="1560"/>
</points>
</Connector>
<Connector class="oracle.dbtools.crest.swingui.relational.TVFKRelation" oid="6050E7DF-C7C5-E7F5-620F-A4AE326303F9" otype="FKIndexAssociation" vid_source="4C7135C7-9CE3-54B3-3ACD-4FF6EB25F8E3" vid_target="C2C8CB38-93EA-AB83-C419-B4134D9A157F">
<hideElementsInCurrentOnly>false</hideElementsInCurrentOnly>
<backgroundColor>-16777216</backgroundColor>
<lineWidth>1</lineWidth>
<points>
<point x="1142" y="2451"/>
<point x="1169" y="2451"/>
</points>
</Connector>
<Connector class="oracle.dbtools.crest.swingui.relational.TVFKRelation" oid="6CC3E193-ED07-23C5-7A77-CD50967FC79B" otype="FKIndexAssociation" vid_source="4C7135C7-9CE3-54B3-3ACD-4FF6EB25F8E3" vid_target="2DC07648-8D7C-E554-BA42-42AB4DE90B75">
<hideElementsInCurrentOnly>false</hideElementsInCurrentOnly>
<backgroundColor>-16777216</backgroundColor>
<lineWidth>1</lineWidth>
<points>
<point x="1142" y="3086"/>
<point x="1171" y="3086"/>
</points>
</Connector>
<Connector class="oracle.dbtools.crest.swingui.relational.TVFKRelation" oid="73A78C58-33DC-7D29-5BEF-AB6206BF5E0F" otype="FKIndexAssociation" vid_source="86D867F0-B399-3746-0BA8-E4B0D1B4F281" vid_target="A02771A7-2D03-6A09-9554-98CE993CCF16">
<hideElementsInCurrentOnly>false</hideElementsInCurrentOnly>
<backgroundColor>-16777216</backgroundColor>
<lineWidth>1</lineWidth>
<points>
<point x="384" y="1006"/>
<point x="384" y="1037"/>
</points>
</Connector>
<Connector class="oracle.dbtools.crest.swingui.relational.TVFKRelation" oid="7DC90BAE-7F96-ECF1-3A7D-A5A630C2C1A6" otype="FKIndexAssociation" vid_source="3AA50766-6FFB-A4E1-E8DF-E3A6E829D3BE" vid_target="458FD6D9-9E22-ECF3-11A5-6EC0B8E2ED80">
<hideElementsInCurrentOnly>false</hideElementsInCurrentOnly>
<backgroundColor>-16777216</backgroundColor>
<lineWidth>1</lineWidth>
<points>
<point x="378" y="217"/>
<point x="378" y="245"/>
</points>
</Connector>
<Connector class="oracle.dbtools.crest.swingui.relational.TVFKRelation" oid="86E80D9F-239D-607C-E365-6242784049A3" otype="FKIndexAssociation" vid_source="95E0A1BD-153B-C40F-C9A1-BB39C988D64E" vid_target="60BCDDB9-D105-CD3E-BE62-D7F69DC8E87A">
<hideElementsInCurrentOnly>false</hideElementsInCurrentOnly>
<backgroundColor>-16777216</backgroundColor>
<lineWidth>1</lineWidth>
<points>
<point x="440" y="1434"/>
<point x="485" y="1434"/>
</points>
</Connector>
<Connector class="oracle.dbtools.crest.swingui.relational.TVFKRelation" oid="8E2036A5-C708-1F59-7379-C1F721DB892C" otype="FKIndexAssociation" vid_source="D90F2EF2-D878-4ED8-A38C-F0C41C790B9E" vid_target="2B33AD59-8CF7-D06A-A7A8-8E64995EAC20">
<hideElementsInCurrentOnly>false</hideElementsInCurrentOnly>
<backgroundColor>-16777216</backgroundColor>
<lineWidth>1</lineWidth>
<points>
<point x="606" y="1912"/>
<point x="760" y="1856"/>
</points>
</Connector>
<Connector class="oracle.dbtools.crest.swingui.relational.TVFKRelation" oid="9CB88E9C-E567-0EBF-7BEE-56AD5C7AE3BC" otype="FKIndexAssociation" vid_source="95E0A1BD-153B-C40F-C9A1-BB39C988D64E" vid_target="D90F2EF2-D878-4ED8-A38C-F0C41C790B9E">
<hideElementsInCurrentOnly>false</hideElementsInCurrentOnly>
<backgroundColor>-16777216</backgroundColor>
<lineWidth>1</lineWidth>
<points>
<point x="388" y="1504"/>
<point x="388" y="1885"/>
</points>
</Connector>
<Connector class="oracle.dbtools.crest.swingui.relational.TVFKRelation" oid="A3FCCF15-68E1-B368-88A7-02A88C00A444" otype="FKIndexAssociation" vid_source="D62E5757-C93C-AFB6-3CCE-93ABE6CE05FE" vid_target="2B33AD59-8CF7-D06A-A7A8-8E64995EAC20">
<hideElementsInCurrentOnly>false</hideElementsInCurrentOnly>
<backgroundColor>-16777216</backgroundColor>
<lineWidth>1</lineWidth>
<points>
<point x="707" y="1744"/>
<point x="760" y="1768"/>
</points>
</Connector>
<Connector class="oracle.dbtools.crest.swingui.relational.TVFKRelation" oid="A6DD3F96-F2E4-15F4-F3CF-539CAF65AE7A" otype="FKIndexAssociation" vid_source="0871EB03-7058-D831-988A-CEB9E9CF4390" vid_target="EFF2A1D3-CD40-E505-8D9B-7C7B834CBA77">
<hideElementsInCurrentOnly>false</hideElementsInCurrentOnly>
<backgroundColor>-16777216</backgroundColor>
<lineWidth>1</lineWidth>
<points>
<point x="412" y="2842"/>
<point x="256" y="3027"/>
</points>
</Connector>
<Connector class="oracle.dbtools.crest.swingui.relational.TVFKRelation" oid="B64D412A-0288-FA1B-87D0-4E0078986A81" otype="FKIndexAssociation" vid_source="4C7135C7-9CE3-54B3-3ACD-4FF6EB25F8E3" vid_target="E9403B8B-FC88-2658-E7B1-D4BCEC1785B1">
<hideElementsInCurrentOnly>false</hideElementsInCurrentOnly>
<backgroundColor>-16777216</backgroundColor>
<lineWidth>1</lineWidth>
<points>
<point x="1142" y="2805"/>
<point x="1169" y="2805"/>
</points>
</Connector>
<Connector class="oracle.dbtools.crest.swingui.relational.TVFKRelation" oid="C3888770-90C6-6258-49F6-F6E7222E0BF3" otype="FKIndexAssociation" vid_source="519947E2-CCFF-C6C5-9BD9-21ABA51A1DDC" vid_target="C81CA3FE-2855-05A6-BE0A-646DB067E5AD">
<hideElementsInCurrentOnly>false</hideElementsInCurrentOnly>
<backgroundColor>-16777216</backgroundColor>
<lineWidth>1</lineWidth>
<points>
<point x="202" y="3593"/>
<point x="202" y="3624"/>
</points>
</Connector>
<Connector class="oracle.dbtools.crest.swingui.relational.TVFKRelation" oid="CBD896D5-45F4-BA65-3616-A06F93D71C40" otype="FKIndexAssociation" vid_source="E5FD6586-A1AA-25B1-6EF9-84E308972405" vid_target="EFF2A1D3-CD40-E505-8D9B-7C7B834CBA77">
<hideElementsInCurrentOnly>false</hideElementsInCurrentOnly>
<backgroundColor>-16777216</backgroundColor>
<lineWidth>1</lineWidth>
<points>
<point x="169" y="2712"/>
<point x="169" y="3027"/>
</points>
</Connector>
<Connector class="oracle.dbtools.crest.swingui.relational.TVFKRelation" oid="D1C77E4E-EC4A-95B0-000F-F80436BDDAE6" otype="FKIndexAssociation" vid_source="519947E2-CCFF-C6C5-9BD9-21ABA51A1DDC" vid_target="F65C957E-E336-C738-C965-DE4DFD522C26">
<hideElementsInCurrentOnly>false</hideElementsInCurrentOnly>
<backgroundColor>-16777216</backgroundColor>
<lineWidth>1</lineWidth>
<points>
<point x="457" y="3537"/>
<point x="552" y="3537"/>
</points>
</Connector>
<Connector class="oracle.dbtools.crest.swingui.relational.TVFKRelation" oid="D3213F8A-19DA-ED98-26D1-149858F8DE77" otype="FKIndexAssociation" vid_source="0871EB03-7058-D831-988A-CEB9E9CF4390" vid_target="17332F65-FED9-0117-4AED-E3EED97A9A7E">
<hideElementsInCurrentOnly>false</hideElementsInCurrentOnly>
<backgroundColor>-16777216</backgroundColor>
<lineWidth>1</lineWidth>
<points>
<point x="583" y="3004"/>
<point x="583" y="3029"/>
</points>
</Connector>
<Connector class="oracle.dbtools.crest.swingui.relational.TVFKRelation" oid="DA472491-623E-4E25-E765-17191EE9D668" otype="FKIndexAssociation" vid_source="222C2E04-E480-F583-B543-A5D5A041EAB2" vid_target="2E1B75AD-C284-E847-3D1A-9A84160DAE37">
<hideElementsInCurrentOnly>false</hideElementsInCurrentOnly>
<backgroundColor>-16777216</backgroundColor>
<lineWidth>1</lineWidth>
<points>
<point x="322" y="2152"/>
<point x="433" y="2152"/>
</points>
</Connector>
<Connector class="oracle.dbtools.crest.swingui.relational.TVFKRelation" oid="DE4564E6-00C3-6F54-33A4-BD1D1F1894FC" otype="FKIndexAssociation" vid_source="4C7135C7-9CE3-54B3-3ACD-4FF6EB25F8E3" vid_target="EFF2A1D3-CD40-E505-8D9B-7C7B834CBA77">
<hideElementsInCurrentOnly>false</hideElementsInCurrentOnly>
<backgroundColor>-16777216</backgroundColor>
<lineWidth>1</lineWidth>
<points>
<point x="801" y="3110"/>
<point x="315" y="3110"/>
</points>
</Connector>
<Connector class="oracle.dbtools.crest.swingui.relational.TVFKRelation" oid="F28D08CB-082F-81AA-02FE-6D3EF839A4CE" otype="FKIndexAssociation" vid_source="95E0A1BD-153B-C40F-C9A1-BB39C988D64E" vid_target="D62E5757-C93C-AFB6-3CCE-93ABE6CE05FE">
<hideElementsInCurrentOnly>false</hideElementsInCurrentOnly>
<backgroundColor>-16777216</backgroundColor>
<lineWidth>1</lineWidth>
<points>
<point x="438" y="1504"/>
<point x="438" y="1600"/>
</points>
</Connector>
<Connector class="oracle.dbtools.crest.swingui.relational.TVFKRelation" oid="F585C378-D490-407D-2A37-83C729468DB3" otype="FKIndexAssociation" vid_source="3AA50766-6FFB-A4E1-E8DF-E3A6E829D3BE" vid_target="1556EB60-D600-CE34-0C18-AFC6D16A0B8B">
<hideElementsInCurrentOnly>false</hideElementsInCurrentOnly>
<backgroundColor>-16777216</backgroundColor>
<lineWidth>1</lineWidth>
<points>
<point x="173" y="217"/>
<point x="173" y="245"/>
</points>
</Connector>
</connectors>
</Diagram>